MANIFEST.in
README.rst
setup.cfg
setup.py
cs/__init__.py
cs.dxfeatured.egg-info/PKG-INFO
cs.dxfeatured.egg-info/SOURCES.txt
cs.dxfeatured.egg-info/dependency_links.txt
cs.dxfeatured.egg-info/entry_points.txt
cs.dxfeatured.egg-info/namespace_packages.txt
cs.dxfeatured.egg-info/not-zip-safe
cs.dxfeatured.egg-info/requires.txt
cs.dxfeatured.egg-info/top_level.txt
cs/dxfeatured/INTEGRATION.txt
cs/dxfeatured/README.txt
cs/dxfeatured/__init__.py
cs/dxfeatured/configure.zcml
cs/dxfeatured/featured.py
cs/dxfeatured/permissions.zcml
cs/dxfeatured/rebuild_i18n.sh
cs/dxfeatured/tests.py
cs/dxfeatured/browser/__init__.py
cs/dxfeatured/browser/configure.zcml
cs/dxfeatured/locales/README.txt
cs/dxfeatured/locales/cs.dxfeatured-manual.pot
cs/dxfeatured/locales/cs.dxfeatured.pot
cs/dxfeatured/locales/plone.pot
cs/dxfeatured/locales/es/LC_MESSAGES/cs.dxfeatured.po
cs/dxfeatured/locales/es/LC_MESSAGES/plone.po
cs/dxfeatured/locales/eu/LC_MESSAGES/cs.dxfeatured.po
cs/dxfeatured/locales/eu/LC_MESSAGES/plone.po
cs/dxfeatured/models/featured.xml
cs/dxfeatured/profiles/default/diff_tool.xml
cs/dxfeatured/profiles/default/metadata.xml
cs/dxfeatured/profiles/default/rolemap.xml
cs/dxfeatured/profiles/default/types.xml
cs/dxfeatured/profiles/default/types/Featured.xml
cs/dxfeatured/templates/README.txt
cs/dxfeatured/templates/featuredview.pt
docs/HISTORY.txt
docs/INSTALL.txt
docs/LICENSE.GPL
docs/LICENSE.txt