Metadata-Version: 1.1
Name: cs.dxfeatured
Version: 1.1
Summary: Dexterity Featured Element
Home-page: https://github.com/codesyntax/cs.dxfeatured
Author: Mikel Larreategi
Author-email: mlarreategi@codesyntax.com
License: GPL
Platform: UNKNOWN
Classifier: Framework :: Plone
Classifier: Programming Language :: Python
Classifier: Topic :: Software Development :: Libraries :: Python Modules
